asyncord-0.13.19.dist-info/METADATA
asyncord-0.13.19.dist-info/WHEEL
asyncord-0.13.19.dist-info/entry_points.txt
asyncord-0.13.19.dist-info/licenses/LICENSE
asyncord/__init__.py
asyncord/base64_image.py
asyncord/client/__init__.py
asyncord/client/applications/__init__.py
asyncord/client/applications/models/__init__.py
asyncord/client/applications/models/common.py
asyncord/client/applications/models/requests.py
asyncord/client/applications/models/responses.py
asyncord/client/applications/resources.py
asyncord/client/auth/__init__.py
asyncord/client/auth/models.py
asyncord/client/auth/resources.py
asyncord/client/bans/__init__.py
asyncord/client/bans/models/__init__.py
asyncord/client/bans/models/responses.py
asyncord/client/bans/resources.py
asyncord/client/channels/__init__.py
asyncord/client/channels/models/__init__.py
asyncord/client/channels/models/common.py
asyncord/client/channels/models/requests/__init__.py
asyncord/client/channels/models/requests/creation.py
asyncord/client/channels/models/requests/updating.py
asyncord/client/channels/models/responses.py
asyncord/client/channels/resources.py
asyncord/client/commands/__init__.py
asyncord/client/commands/models/__init__.py
asyncord/client/commands/models/common.py
asyncord/client/commands/models/requests.py
asyncord/client/commands/models/responses.py
asyncord/client/commands/resources.py
asyncord/client/emojis/__init__.py
asyncord/client/emojis/models/__init__.py
asyncord/client/emojis/models/requests.py
asyncord/client/emojis/models/responses.py
asyncord/client/emojis/resources.py
asyncord/client/guild_templates/__init__.py
asyncord/client/guild_templates/models/__init__.py
asyncord/client/guild_templates/models/requests.py
asyncord/client/guild_templates/models/responses.py
asyncord/client/guild_templates/resources.py
asyncord/client/guilds/__init__.py
asyncord/client/guilds/models/__init__.py
asyncord/client/guilds/models/common.py
asyncord/client/guilds/models/requests.py
asyncord/client/guilds/models/responses.py
asyncord/client/guilds/resources.py
asyncord/client/http/__init__.py
asyncord/client/http/client.py
asyncord/client/http/error_codes.py
asyncord-0.13.19.dist-info/RECORD
