Metadata-Version: 2.1
Name: asyncord
Version: 0.13.19
Summary: A smart and powerful base for creating discord bots and interaction with the API.
Author-Email: Vadim Suharnikov <vsuharnikov@gmail.com>
License: MIT
Project-URL: homepage, https://github.com/suharnikov/asyncord
Project-URL: repository, https://github.com/suharnikov/asyncord
Requires-Python: >=3.12.0
Requires-Dist: yarl>=1.8.1
Requires-Dist: rich>=12.5.1
Requires-Dist: pydantic>=2.4.2
Requires-Dist: aiohttp<4
Requires-Dist: filetype>=1.2.0
Requires-Dist: fbenum>=1.0.1
